rdfhelpers/__init__.py
rdfhelpers/core/__init__.py
rdfhelpers/core/basics.py
rdfhelpers/core/cbd.py
rdfhelpers/core/composable.py
rdfhelpers/core/labels.py
rdfhelpers/core/templated.py
rdfhelpers/core/time.py
rdfhelpers/core/uri.py
rdfhelpers/experimental/__init__.py
rdfhelpers/experimental/constructor.py
rdfhelpers/producers/__init__.py
rdfhelpers/producers/apis/__init__.py
rdfhelpers/producers/apis/core.py
rdfhelpers/producers/apis/geonames.py
rdfhelpers/producers/common/__init__.py
rdfhelpers/producers/common/interface.py
rdfhelpers/producers/common/utilities.py
rdfhelpers/producers/consumers/__init__.py
rdfhelpers/producers/consumers/csvexporter.py
rdfhelpers/producers/consumers/tempfileconsumer.py
rdfhelpers/producers/generators/__init__.py
rdfhelpers/producers/generators/geonames.py
rdfhelpers/producers/generators/mysqlgenerator.py
rdfhelpers/producers/harvesters/__init__.py
rdfhelpers/producers/harvesters/filesystem.py
rdfhelpers/producers/harvesters/webcrawler.py
rdfhelpers/producers/harvesters/xmpharvester.py
rdfhelpers/producers/mappers/__init__.py
rdfhelpers/producers/mappers/csvreadermapper.py
rdfhelpers/producers/mappers/pandasmapper.py
rdfhelpers/producers/mappers/r2rmlmapper.py
rdfhelpers/producers/mappers/tinyrmlmapper.py
rdfhelpers/producers/mappers/xsltmapper.py
rdfhelpers-0.7.8.dist-info/licenses/LICENSE
rdfhelpers-0.7.8.dist-info/METADATA
rdfhelpers-0.7.8.dist-info/WHEEL
rdfhelpers-0.7.8.dist-info/top_level.txt
rdfhelpers-0.7.8.dist-info/RECORD
