Metadata-Version: 2.4
Name: rdfhelpers
Version: 0.7.8
Summary: Useful stuff when programming with RDFLib
Author-email: Ora Lassila <ora@somanyaircraft.com>
License-Expression: BSD-3-Clause
Project-URL: Homepage, https://gitlab.com/somanyaircraft/rdfhelpers
Classifier: Development Status :: 4 - Beta
Classifier: Programming Language :: Python :: 3
Classifier: Operating System :: OS Independent
Requires-Python: >=3.9
License-File: LICENSE
Dynamic: license-file
